GConvNet/__init__.py
GConvNet/main.py
gconvnet-0.0.3.dist-info/licenses/LICENSE
gconvnet-0.0.3.dist-info/METADATA
gconvnet-0.0.3.dist-info/WHEEL
gconvnet-0.0.3.dist-info/top_level.txt
gconvnet-0.0.3.dist-info/RECORD
