Metadata-Version: 2.4
Name: GConvNet
Version: 0.0.3
Summary: GConvNet
Author-email: sobazino <sobazino@gmail.com>
License: Apache-2.0 license
Classifier: Programming Language :: Python :: 3
License-File: LICENSE
Dynamic: license-file
